LinearRegression/__init__.py
LinearRegression/plot.py
LinearRegression/regression.py
LinearRegression/run_regression.py
LinearRegression/utils.py
MultipleRegression/__init__.py
MultipleRegression/plot.py
MultipleRegression/regression.py
MultipleRegression/run_regression.py
MultipleRegression/utils.py
TimeSeriesRegression/Exponential_Smoothing.py
TimeSeriesRegression/__init__.py
TimeSeriesRegression/arch.py
TimeSeriesRegression/arima.py
TimeSeriesRegression/garch.py
TimeSeriesRegression/holt_winters.py
TimeSeriesRegression/lstm_model.py
TimeSeriesRegression/prophet.py
TimeSeriesRegression/run_lstm.py
TimeSeriesRegression/sarima.py
TimeSeriesRegression/var.py
econometrics_python-1.0.2.dist-info/LICENSE
econometrics_python-1.0.2.dist-info/METADATA
econometrics_python-1.0.2.dist-info/WHEEL
econometrics_python-1.0.2.dist-info/top_level.txt
econometrics_python-1.0.2.dist-info/RECORD
