Metadata-Version: 2.1
Name: econometrics-python
Version: 1.0.2
Summary: Package for econometric.
Home-page: https://github.com/Trantamming/econometrics
Author: Trần Minh Tâm
Author-email: tam.ming.zhan@gmail.com
License: UNKNOWN
Platform: UNKNOWN
Classifier: Programming Language :: Python :: 3
Classifier: License :: OSI Approved :: MIT License
Classifier: Operating System :: OS Independent
Requires-Python: >=3.6
License-File: LICENSE
Requires-Dist: pandas
Requires-Dist: numpy
Requires-Dist: statsmodels
Requires-Dist: matplotlib
